svmon_client/__init__.py
svmon_client/config.json
svmon_client/json_operations.py
svmon_client/operating_system_parser.py
svmon_client/remoteConfig.py
svmon_client/report.py
svmon_client/services.py
svmon_client/svmon_eudat_eu.cer
svmon_client/token.json
svmon_client-2.4.5.data/scripts/svmon
svmon_client-2.4.5.dist-info/LICENSE
svmon_client-2.4.5.dist-info/METADATA
svmon_client-2.4.5.dist-info/WHEEL
svmon_client-2.4.5.dist-info/top_level.txt
svmon_client-2.4.5.dist-info/RECORD
