Metadata-Version: 2.1
Name: svmon-client
Version: 2.4.5
Summary: This is a python implementation of SVMON client
Home-page: https://gitlab.eudat.eu/EUDAT-TOOLS/SVMON/pysvmon
Author: Jie Yuan
Author-email: jie.yuan@kit.edu
Maintainer: Agustin Pane
Maintainer-email: agustin.pane@kit.edu
License: MIT License
Platform: all
Classifier: Development Status :: 4 - Beta
Classifier: Operating System :: OS Independent
Classifier: Intended Audience :: Developers
Classifier: License :: OSI Approved :: MIT License
Classifier: Programming Language :: Python
Classifier: Programming Language :: Python :: Implementation
Classifier: Programming Language :: Python :: 2.7
Classifier: Topic :: Software Development :: Libraries
License-File: LICENSE
Requires-Dist: python-dotenv
Requires-Dist: requests
